{
    "TCP_10s_Repetitions-9-20250609-23:46:48-97540" : {
        "attributes" : {
            "configname" : "TCP_10s_Repetitions",
            "datetime" : "20250609-23:46:48",
            "datetimef" : "20250609-234648",
            "experiment" : "TCP_10s_Repetitions",
            "inifile" : "omnetpp.ini",
            "iterationvars" : "",
            "iterationvarsd" : "",
            "iterationvarsf" : "",
            "measurement" : "",
            "network" : "SimpleTcpNetwork",
            "processid" : "97540",
            "repetition" : "9",
            "replication" : "#9",
            "resultdir" : "results",
            "runnumber" : "9",
            "seedset" : "9"
        },
        "itervars" : {
        },
        "config" : [
            { "image-path" : "../inet4.5/images" },
            { "description" : "10 TCP runs with different seeds" },
            { "sim-time-limit" : "10s" },
            { "repeat" : "10" },
            { "seed-set" : "9" },
            { "**.client.app[0].sendBytes" : "10MiB" },
            { "**.client.app[0].tOpen" : "exponential(0.1s)" },
            { "**.client.app[0].tSend" : "exponential(0.1s)" },
            { "**.client.app[0].tClose" : "-1s" },
            { "**.vector-recording" : "true" },
            { "output-vector-file" : "results/TCP_10s_Repetitions_run9.vec" },
            { "output-scalar-file" : "results/TCP_10s_Repetitions_run9.json" },
            { "network" : "SimpleTcpNetwork" },
            { "sim-time-limit" : "1000s" },
            { "**.vector-recording" : "true" },
            { "**.tcp.typename" : "Tcp" },
            { "**.tcp.tcpAlgorithmClass" : "\"TcpNewReno\"" },
            { "**.tcp.windowScalingSupport" : "true" },
            { "**.tcp.mss" : "1460" },
            { "**.tcp.advertisedWindow" : "1460000" },
            { "**.ppp[*].queue.typename" : "DropTailQueue" },
            { "**.ppp[*].queue.packetCapacity" : "10" },
            { "**.client.numApps" : "1" },
            { "**.client.app[0].typename" : "TcpSessionApp" },
            { "**.client.app[0].localAddress" : "\"\"" },
            { "**.client.app[0].connectAddress" : "\"server\"" },
            { "**.client.app[0].connectPort" : "1000" },
            { "**.client.app[0].tOpen" : "0s" },
            { "**.client.app[0].tSend" : "0s" },
            { "**.client.app[0].sendBytes" : "1GiB" },
            { "**.client.app[0].tClose" : "-1s" },
            { "**.server.numApps" : "1" },
            { "**.server.app[0].typename" : "TcpSinkApp" },
            { "**.server.app[0].localPort" : "1000" }
        ],
        "vectors" : [
            {
                "module" : "SimpleTcpNetwork.server.app[0]",
                "name" : "packetReceived:vector(packetBytes)",
                "attributes" : {
                    "checkSignals" : "false",
                    "interpolationmode" : "none",
                    "recordingmode" : "vector(packetBytes)",
                    "source" : "packetReceived",
                    "title" : "packets received, packetBytes"
                },
                "time" : [1.214354834482, 2.026786834482, 2.038842834482, 2.839218834482, 2.851274834482, 2.863330834482, 2.875386834482, 3.651650834482, 3.663706834482, 3.675762834482, 
                    3.687818834482, 3.699874834482, 3.711930834482, 3.723986834482, 3.736042834482, 4.464082834482, 4.476138834482, 4.488194834482, 4.500250834482, 4.512306834482, 
                    4.524362834482, 4.536418834482, 4.548474834482, 4.560530834482, 4.572586834482, 4.584642834482, 4.596698834482, 4.608754834482, 4.620810834482, 4.632866834482, 
                    4.644922834482, 5.276514834482, 5.288570834482, 5.300626834482, 5.312682834482, 5.324738834482, 5.336794834482, 5.348850834482, 5.360906834482, 5.372962834482, 
                    5.385018834482, 5.397074834482, 5.409130834482, 5.421186834482, 5.433242834482, 5.445298834482, 5.457354834482, 5.469410834482, 5.481466834482, 5.493522834482, 
                    5.505578834482, 5.517634834482, 6.462682834482, 7.275114834482, 8.087546834482, 8.899978834482, 9.712410834482],
                "value" : [1460, 1460, 1460, 1460, 1460, 1460, 1460, 1460, 1460, 1460, 
                    1460, 1460, 1460, 1460, 1460, 1460, 1460, 1460, 1460, 1460, 
                    1460, 1460, 1460, 1460, 1460, 1460, 1460, 1460, 1460, 1460, 
                    1460, 1460, 1460, 1460, 1460, 1460, 1460, 1460, 1460, 1460, 
                    1460, 1460, 1460, 1460, 1460, 1460, 1460, 1460, 1460, 1460, 
                    1460, 1460, 2920, 2920, 2920, 2920, 2920],
                "eventnumber" : [36, 52, 59, 84, 91, 98, 105, 148, 155, 162, 
                    169, 176, 183, 190, 197, 276, 283, 290, 297, 304, 
                    311, 318, 325, 332, 339, 346, 353, 360, 367, 374, 
                    381, 526, 533, 540, 547, 554, 561, 568, 575, 582, 
                    589, 596, 603, 610, 617, 624, 631, 638, 645, 652, 
                    659, 666, 1085, 1275, 1381, 1460, 1515]
            }
        ]
    }
}
