{
    "TCP_10s_Repetitions-0-20250609-23:46:46-97529" : {
        "attributes" : {
            "configname" : "TCP_10s_Repetitions",
            "datetime" : "20250609-23:46:46",
            "datetimef" : "20250609-234646",
            "experiment" : "TCP_10s_Repetitions",
            "inifile" : "omnetpp.ini",
            "iterationvars" : "",
            "iterationvarsd" : "",
            "iterationvarsf" : "",
            "measurement" : "",
            "network" : "SimpleTcpNetwork",
            "processid" : "97529",
            "repetition" : "0",
            "replication" : "#0",
            "resultdir" : "results",
            "runnumber" : "0",
            "seedset" : "0"
        },
        "itervars" : {
        },
        "config" : [
            { "image-path" : "../inet4.5/images" },
            { "description" : "10 TCP runs with different seeds" },
            { "sim-time-limit" : "10s" },
            { "repeat" : "10" },
            { "seed-set" : "0" },
            { "**.client.app[0].sendBytes" : "10MiB" },
            { "**.client.app[0].tOpen" : "exponential(0.1s)" },
            { "**.client.app[0].tSend" : "exponential(0.1s)" },
            { "**.client.app[0].tClose" : "-1s" },
            { "**.vector-recording" : "true" },
            { "output-vector-file" : "results/TCP_10s_Repetitions_run0.vec" },
            { "output-scalar-file" : "results/TCP_10s_Repetitions_run0.json" },
            { "network" : "SimpleTcpNetwork" },
            { "sim-time-limit" : "1000s" },
            { "**.vector-recording" : "true" },
            { "**.tcp.typename" : "Tcp" },
            { "**.tcp.tcpAlgorithmClass" : "\"TcpNewReno\"" },
            { "**.tcp.windowScalingSupport" : "true" },
            { "**.tcp.mss" : "1460" },
            { "**.tcp.advertisedWindow" : "1460000" },
            { "**.ppp[*].queue.typename" : "DropTailQueue" },
            { "**.ppp[*].queue.packetCapacity" : "10" },
            { "**.client.numApps" : "1" },
            { "**.client.app[0].typename" : "TcpSessionApp" },
            { "**.client.app[0].localAddress" : "\"\"" },
            { "**.client.app[0].connectAddress" : "\"server\"" },
            { "**.client.app[0].connectPort" : "1000" },
            { "**.client.app[0].tOpen" : "0s" },
            { "**.client.app[0].tSend" : "0s" },
            { "**.client.app[0].sendBytes" : "1GiB" },
            { "**.client.app[0].tClose" : "-1s" },
            { "**.server.numApps" : "1" },
            { "**.server.app[0].typename" : "TcpSinkApp" },
            { "**.server.app[0].localPort" : "1000" }
        ],
        "vectors" : [
            {
                "module" : "SimpleTcpNetwork.server.app[0]",
                "name" : "packetReceived:vector(packetBytes)",
                "attributes" : {
                    "checkSignals" : "false",
                    "interpolationmode" : "none",
                    "recordingmode" : "vector(packetBytes)",
                    "source" : "packetReceived",
                    "title" : "packets received, packetBytes"
                },
                "time" : [1.292899450457, 2.105331450457, 2.117387450457, 2.917763450457, 2.929819450457, 2.941875450457, 2.953931450457, 3.730195450457, 3.742251450457, 3.754307450457, 
                    3.766363450457, 3.778419450457, 3.790475450457, 3.802531450457, 3.814587450457, 4.542627450457, 4.554683450457, 4.566739450457, 4.578795450457, 4.590851450457, 
                    4.602907450457, 4.614963450457, 4.627019450457, 4.639075450457, 4.651131450457, 4.663187450457, 4.675243450457, 4.687299450457, 4.699355450457, 4.711411450457, 
                    4.723467450457, 5.355059450457, 5.367115450457, 5.379171450457, 5.391227450457, 5.403283450457, 5.415339450457, 5.427395450457, 5.439451450457, 5.451507450457, 
                    5.463563450457, 5.475619450457, 5.487675450457, 5.499731450457, 5.511787450457, 5.523843450457, 5.535899450457, 5.547955450457, 5.560011450457, 5.572067450457, 
                    5.584123450457, 5.596179450457, 6.541227450457, 7.353659450457, 8.166091450457, 8.978523450457, 9.790955450457],
                "value" : [1460, 1460, 1460, 1460, 1460, 1460, 1460, 1460, 1460, 1460, 
                    1460, 1460, 1460, 1460, 1460, 1460, 1460, 1460, 1460, 1460, 
                    1460, 1460, 1460, 1460, 1460, 1460, 1460, 1460, 1460, 1460, 
                    1460, 1460, 1460, 1460, 1460, 1460, 1460, 1460, 1460, 1460, 
                    1460, 1460, 1460, 1460, 1460, 1460, 1460, 1460, 1460, 1460, 
                    1460, 1460, 2920, 2920, 2920, 2920, 2920],
                "eventnumber" : [36, 52, 59, 84, 91, 98, 105, 148, 155, 162, 
                    169, 176, 183, 190, 197, 276, 283, 290, 297, 304, 
                    311, 318, 325, 332, 339, 346, 353, 360, 367, 374, 
                    381, 526, 533, 540, 547, 554, 561, 568, 575, 582, 
                    589, 596, 603, 610, 617, 624, 631, 638, 645, 652, 
                    659, 666, 1085, 1275, 1381, 1460, 1515]
            }
        ]
    }
}
