{
    "TCP_10s_Repetitions-3-20250609-23:46:47-97534" : {
        "attributes" : {
            "configname" : "TCP_10s_Repetitions",
            "datetime" : "20250609-23:46:47",
            "datetimef" : "20250609-234647",
            "experiment" : "TCP_10s_Repetitions",
            "inifile" : "omnetpp.ini",
            "iterationvars" : "",
            "iterationvarsd" : "",
            "iterationvarsf" : "",
            "measurement" : "",
            "network" : "SimpleTcpNetwork",
            "processid" : "97534",
            "repetition" : "3",
            "replication" : "#3",
            "resultdir" : "results",
            "runnumber" : "3",
            "seedset" : "3"
        },
        "itervars" : {
        },
        "config" : [
            { "image-path" : "../inet4.5/images" },
            { "description" : "10 TCP runs with different seeds" },
            { "sim-time-limit" : "10s" },
            { "repeat" : "10" },
            { "seed-set" : "3" },
            { "**.client.app[0].sendBytes" : "10MiB" },
            { "**.client.app[0].tOpen" : "exponential(0.1s)" },
            { "**.client.app[0].tSend" : "exponential(0.1s)" },
            { "**.client.app[0].tClose" : "-1s" },
            { "**.vector-recording" : "true" },
            { "output-vector-file" : "results/TCP_10s_Repetitions_run3.vec" },
            { "output-scalar-file" : "results/TCP_10s_Repetitions_run3.json" },
            { "network" : "SimpleTcpNetwork" },
            { "sim-time-limit" : "1000s" },
            { "**.vector-recording" : "true" },
            { "**.tcp.typename" : "Tcp" },
            { "**.tcp.tcpAlgorithmClass" : "\"TcpNewReno\"" },
            { "**.tcp.windowScalingSupport" : "true" },
            { "**.tcp.mss" : "1460" },
            { "**.tcp.advertisedWindow" : "1460000" },
            { "**.ppp[*].queue.typename" : "DropTailQueue" },
            { "**.ppp[*].queue.packetCapacity" : "10" },
            { "**.client.numApps" : "1" },
            { "**.client.app[0].typename" : "TcpSessionApp" },
            { "**.client.app[0].localAddress" : "\"\"" },
            { "**.client.app[0].connectAddress" : "\"server\"" },
            { "**.client.app[0].connectPort" : "1000" },
            { "**.client.app[0].tOpen" : "0s" },
            { "**.client.app[0].tSend" : "0s" },
            { "**.client.app[0].sendBytes" : "1GiB" },
            { "**.client.app[0].tClose" : "-1s" },
            { "**.server.numApps" : "1" },
            { "**.server.app[0].typename" : "TcpSinkApp" },
            { "**.server.app[0].localPort" : "1000" }
        ],
        "vectors" : [
            {
                "module" : "SimpleTcpNetwork.server.app[0]",
                "name" : "packetReceived:vector(packetBytes)",
                "attributes" : {
                    "checkSignals" : "false",
                    "interpolationmode" : "none",
                    "recordingmode" : "vector(packetBytes)",
                    "source" : "packetReceived",
                    "title" : "packets received, packetBytes"
                },
                "time" : [1.293340239089, 2.105772239089, 2.117828239089, 2.918204239089, 2.930260239089, 2.942316239089, 2.954372239089, 3.730636239089, 3.742692239089, 3.754748239089, 
                    3.766804239089, 3.778860239089, 3.790916239089, 3.802972239089, 3.815028239089, 4.543068239089, 4.555124239089, 4.567180239089, 4.579236239089, 4.591292239089, 
                    4.603348239089, 4.615404239089, 4.627460239089, 4.639516239089, 4.651572239089, 4.663628239089, 4.675684239089, 4.687740239089, 4.699796239089, 4.711852239089, 
                    4.723908239089, 5.355500239089, 5.367556239089, 5.379612239089, 5.391668239089, 5.403724239089, 5.415780239089, 5.427836239089, 5.439892239089, 5.451948239089, 
                    5.464004239089, 5.476060239089, 5.488116239089, 5.500172239089, 5.512228239089, 5.524284239089, 5.536340239089, 5.548396239089, 5.560452239089, 5.572508239089, 
                    5.584564239089, 5.596620239089, 6.541668239089, 7.354100239089, 8.166532239089, 8.978964239089, 9.791396239089],
                "value" : [1460, 1460, 1460, 1460, 1460, 1460, 1460, 1460, 1460, 1460, 
                    1460, 1460, 1460, 1460, 1460, 1460, 1460, 1460, 1460, 1460, 
                    1460, 1460, 1460, 1460, 1460, 1460, 1460, 1460, 1460, 1460, 
                    1460, 1460, 1460, 1460, 1460, 1460, 1460, 1460, 1460, 1460, 
                    1460, 1460, 1460, 1460, 1460, 1460, 1460, 1460, 1460, 1460, 
                    1460, 1460, 2920, 2920, 2920, 2920, 2920],
                "eventnumber" : [36, 52, 59, 84, 91, 98, 105, 148, 155, 162, 
                    169, 176, 183, 190, 197, 276, 283, 290, 297, 304, 
                    311, 318, 325, 332, 339, 346, 353, 360, 367, 374, 
                    381, 526, 533, 540, 547, 554, 561, 568, 575, 582, 
                    589, 596, 603, 610, 617, 624, 631, 638, 645, 652, 
                    659, 666, 1085, 1275, 1381, 1460, 1515]
            }
        ]
    }
}
